{
  "id": "puzzle_004",
  "title": "Puzzle 4",
  "rows": 5,
  "cols": 5,
  "solution": [
    [
      "G",
      "A",
      "M",
      "E",
      null
    ],
    [
      "A",
      "R",
      "E",
      null,
      "C"
    ],
    [
      "M",
      "E",
      "D",
      "I",
      "A"
    ],
    [
      "E",
      null,
      "I",
      "T",
      "S"
    ],
    [
      null,
      "C",
      "A",
      "S",
      "E"
    ]
  ],
  "prefilled": {
    "easy": [
      [
        3,
        3
      ],
      [
        0,
        1
      ],
      [
        1,
        0
      ],
      [
        3,
        4
      ],
      [
        2,
        1
      ]
    ],
    "medium": [
      [
        3,
        3
      ],
      [
        0,
        1
      ],
      [
        1,
        0
      ]
    ],
    "hard": [
      [
        3,
        3
      ]
    ]
  },
  "clues": {
    "across": [
      {
        "num": 1,
        "row": 0,
        "col": 0,
        "clue": {
          "en": "A playful or competitive activity.",
          "zh": "一种有趣的或竞争性的活动。"
        }
      },
      {
        "num": 4,
        "row": 1,
        "col": 0,
        "clue": {
          "en": "An accepted (but deprecated and rarely used) SI unit of area equal to 100 square metres, or a former unit of approximately the same extent. Symbol: a.",
          "zh": "一种已接受（但已弃用且很少使用）的 SI 面积单位，等于 100 平方米，或大致相同范围的以前单位。符号：A."
        }
      },
      {
        "num": 6,
        "row": 2,
        "col": 0,
        "clue": {
          "en": "The middle layer of the wall of a blood vessel or lymph vessel which is composed of connective and muscular tissue.",
          "zh": "血管或淋巴管壁的中间层，由结缔组织和肌肉组织组成。"
        }
      },
      {
        "num": 8,
        "row": 3,
        "col": 2,
        "clue": {
          "en": "One who is neither a he nor a she; a creature; a dehumanized being.",
          "zh": "一个既不是他也不是她的人；一个生物；一个非人化的存在。"
        }
      },
      {
        "num": 9,
        "row": 4,
        "col": 1,
        "clue": {
          "en": "An actual event, situation, or fact.",
          "zh": "实际事件、情况或事实。"
        }
      }
    ],
    "down": [
      {
        "num": 1,
        "row": 0,
        "col": 0,
        "clue": {
          "en": "A playful or competitive activity.",
          "zh": "一种有趣的或竞争性的活动。"
        }
      },
      {
        "num": 2,
        "row": 0,
        "col": 1,
        "clue": {
          "en": "An accepted (but deprecated and rarely used) SI unit of area equal to 100 square metres, or a former unit of approximately the same extent. Symbol: a.",
          "zh": "一种已接受（但已弃用且很少使用）的 SI 面积单位，等于 100 平方米，或大致相同范围的以前单位。符号：A."
        }
      },
      {
        "num": 3,
        "row": 0,
        "col": 2,
        "clue": {
          "en": "The middle layer of the wall of a blood vessel or lymph vessel which is composed of connective and muscular tissue.",
          "zh": "血管或淋巴管壁的中间层，由结缔组织和肌肉组织组成。"
        }
      },
      {
        "num": 5,
        "row": 1,
        "col": 4,
        "clue": {
          "en": "An actual event, situation, or fact.",
          "zh": "实际事件、情况或事实。"
        }
      },
      {
        "num": 7,
        "row": 2,
        "col": 3,
        "clue": {
          "en": "One who is neither a he nor a she; a creature; a dehumanized being.",
          "zh": "一个既不是他也不是她的人；一个生物；一个非人化的存在。"
        }
      }
    ]
  }
}