{
  "id": "puzzle_054",
  "title": "Hard #4",
  "rows": 9,
  "cols": 9,
  "solution": [
    [
      null,
      null,
      "P",
      null,
      null,
      "S",
      null,
      null,
      "M"
    ],
    [
      "B",
      "A",
      "R",
      null,
      "R",
      "A",
      "T",
      "I",
      "O"
    ],
    [
      null,
      "N",
      "O",
      "V",
      "E",
      "L",
      null,
      "N",
      "M"
    ],
    [
      "A",
      "X",
      null,
      "E",
      "S",
      "T",
      "A",
      "T",
      "E"
    ],
    [
      "S",
      "I",
      "G",
      "H",
      "T",
      null,
      "P",
      "E",
      "N"
    ],
    [
      "P",
      "E",
      "R",
      "I",
      "O",
      "D",
      null,
      "N",
      "T"
    ],
    [
      "E",
      "T",
      null,
      "C",
      "R",
      "O",
      "S",
      "S",
      null
    ],
    [
      "C",
      "Y",
      "C",
      "L",
      "E",
      null,
      "K",
      "E",
      "Y"
    ],
    [
      "T",
      null,
      null,
      "E",
      null,
      null,
      "Y",
      null,
      null
    ]
  ],
  "prefilled": {
    "easy": [
      [
        7,
        4
      ],
      [
        3,
        3
      ],
      [
        3,
        7
      ],
      [
        3,
        1
      ],
      [
        5,
        7
      ],
      [
        2,
        5
      ],
      [
        6,
        0
      ],
      [
        8,
        6
      ],
      [
        5,
        5
      ],
      [
        0,
        8
      ],
      [
        1,
        2
      ],
      [
        7,
        3
      ],
      [
        1,
        0
      ],
      [
        6,
        7
      ],
      [
        3,
        5
      ]
    ],
    "medium": [
      [
        7,
        4
      ],
      [
        3,
        3
      ],
      [
        3,
        7
      ],
      [
        3,
        1
      ],
      [
        5,
        7
      ],
      [
        2,
        5
      ],
      [
        6,
        0
      ],
      [
        8,
        6
      ],
      [
        5,
        5
      ]
    ],
    "hard": [
      [
        7,
        4
      ],
      [
        3,
        3
      ],
      [
        3,
        7
      ],
      [
        3,
        1
      ]
    ]
  },
  "clues": {
    "across": [
      {
        "num": 4,
        "row": 1,
        "col": 0,
        "clue": {
          "en": "A solid, more or less rigid object of metal or wood with a uniform cross-section smaller than its length.",
          "zh": "酒吧"
        },
        "level": 4
      },
      {
        "num": 6,
        "row": 1,
        "col": 4,
        "clue": {
          "en": "A number representing a comparison between two named things.",
          "zh": "比率"
        },
        "level": 5
      },
      {
        "num": 8,
        "row": 2,
        "col": 1,
        "clue": {
          "en": "Newly made, formed or evolved; having no precedent; of recent origin; new.",
          "zh": "小说"
        },
        "level": 4
      },
      {
        "num": 12,
        "row": 3,
        "col": 3,
        "clue": {
          "en": "The collective property and liabilities of someone, especially a deceased person.",
          "zh": "财产"
        },
        "level": 5
      },
      {
        "num": 14,
        "row": 4,
        "col": 0,
        "clue": {
          "en": "(in the singular) The ability to see.",
          "zh": "视线"
        },
        "level": 1
      },
      {
        "num": 16,
        "row": 4,
        "col": 6,
        "clue": {
          "en": "An enclosure (enclosed area) used to contain domesticated animals, especially sheep or cattle.",
          "zh": "钢笔"
        },
        "level": 1
      },
      {
        "num": 17,
        "row": 5,
        "col": 0,
        "clue": {
          "en": "A length of time.",
          "zh": "时期"
        },
        "level": 1
      },
      {
        "num": 21,
        "row": 6,
        "col": 3,
        "clue": {
          "en": "A geometrical figure consisting of two straight lines or bars intersecting each other such that at least one of them is bisected by the other.",
          "zh": "叉"
        },
        "level": 1
      },
      {
        "num": 23,
        "row": 7,
        "col": 0,
        "clue": {
          "en": "An interval of space or time in which one set of events or phenomena is completed.",
          "zh": "循环"
        },
        "level": 4
      },
      {
        "num": 24,
        "row": 7,
        "col": 6,
        "clue": {
          "en": "An object designed to open and close a lock.",
          "zh": "钥匙"
        },
        "level": 1
      }
    ],
    "down": [
      {
        "num": 1,
        "row": 0,
        "col": 2,
        "clue": {
          "en": "An advantage of something, especially when contrasted with its disadvantages (cons).",
          "zh": "专业人士"
        },
        "level": 1
      },
      {
        "num": 2,
        "row": 0,
        "col": 5,
        "clue": {
          "en": "A common substance, chemically consisting mainly of sodium chloride (NaCl), used extensively as a condiment and preservative.",
          "zh": "盐"
        },
        "level": 1
      },
      {
        "num": 3,
        "row": 0,
        "col": 8,
        "clue": {
          "en": "A brief, unspecified amount of time.",
          "zh": "片刻"
        },
        "level": 1
      },
      {
        "num": 5,
        "row": 1,
        "col": 1,
        "clue": {
          "en": "An unpleasant state of mental uneasiness, nervousness, apprehension and obsession or concern about some uncertain event.",
          "zh": "焦虑"
        },
        "level": 4
      },
      {
        "num": 6,
        "row": 1,
        "col": 4,
        "clue": {
          "en": "The act of recovering data or a system from a backup.",
          "zh": "恢复"
        },
        "level": 5
      },
      {
        "num": 7,
        "row": 1,
        "col": 7,
        "clue": {
          "en": "Strained; tightly drawn.",
          "zh": "激烈的"
        },
        "level": 5
      },
      {
        "num": 9,
        "row": 2,
        "col": 3,
        "clue": {
          "en": "A conveyance; a device for carrying or transporting substances, objects or individuals.",
          "zh": "车辆"
        },
        "level": 1
      },
      {
        "num": 11,
        "row": 3,
        "col": 0,
        "clue": {
          "en": "Any specific feature, part, or element of something.",
          "zh": "方面"
        },
        "level": 4
      },
      {
        "num": 22,
        "row": 6,
        "col": 6,
        "clue": {
          "en": "The atmosphere above a given point, especially as visible from the ground during the day.",
          "zh": "天空"
        },
        "level": 1
      }
    ]
  },
  "difficulty": "hard",
  "gridSize": 9,
  "exam": "senior_high"
}